pds/__init__.py
pds/aossrequestsigner/VERSION.txt
pds/aossrequestsigner/__init__.py
pds/aossrequestsigner/credentials.py
pds/aossrequestsigner/errors.py
pds/aossrequestsigner/run.py
pds/aossrequestsigner/utils.py
pds_registry_client-0.4.0.dist-info/licenses/LICENSE.md
pds_registry_client-0.4.0.dist-info/licenses/NOTICE.txt
pds_registry_client-0.4.0.dist-info/METADATA
pds_registry_client-0.4.0.dist-info/WHEEL
pds_registry_client-0.4.0.dist-info/entry_points.txt
pds_registry_client-0.4.0.dist-info/top_level.txt
pds_registry_client-0.4.0.dist-info/zip-safe
pds_registry_client-0.4.0.dist-info/RECORD
