Metadata-Version: 2.4
Name: pds.registry-client
Version: 0.4.0
Summary: A simple PDS Registry Client which authenticates users with PDS single sign-on and signs requests to the serverless OpenSearch (AOSS) hosting the Registry database.
Home-page: https://github.com/NASA-PDS/registry-client
Download-URL: https://github.com/NASA-PDS/registry-client/releases/
Author: PDS Engineering Node
Author-email: pds_operator@jpl.nasa.gov
License: apache-2.0
Keywords: pds,planetary data,various,other,keywords
Classifier: Programming Language :: Python :: 3
Classifier: Programming Language :: Python :: 3.12
Classifier: Programming Language :: Python :: 3.13
Classifier: Operating System :: OS Independent
Requires-Python: >=3.12
License-File: LICENSE.md
License-File: NOTICE.txt
Requires-Dist: argparse~=1.4.0
Requires-Dist: opensearch-py~=2.6
Requires-Dist: requests~=2.28
Requires-Dist: retry~=0.9.2
Requires-Dist: tqdm~=4.66.2
Requires-Dist: boto3~=1.34.91
Requires-Dist: botocore~=1.34.91
Requires-Dist: requests-aws4auth~=1.2.3
Requires-Dist: setuptools~=80.9.0
Provides-Extra: dev
Requires-Dist: flake8~=7.3.0; extra == "dev"
Requires-Dist: flake8-bugbear~=24.12.12; extra == "dev"
Requires-Dist: flake8-docstrings~=1.7.0; extra == "dev"
Requires-Dist: pep8-naming~=0.13.3; extra == "dev"
Requires-Dist: mypy~=1.14.1; extra == "dev"
Requires-Dist: pydocstyle~=6.3.0; extra == "dev"
Requires-Dist: coverage~=7.3.0; extra == "dev"
Requires-Dist: pytest~=7.4.0; extra == "dev"
Requires-Dist: pytest-cov~=4.1.0; extra == "dev"
Requires-Dist: pytest-watch~=4.2.0; extra == "dev"
Requires-Dist: pytest-xdist~=3.3.1; extra == "dev"
Requires-Dist: pre-commit~=3.3.3; extra == "dev"
Requires-Dist: sphinx~=8.2.3; extra == "dev"
Requires-Dist: sphinx-rtd-theme~=3.0.2; extra == "dev"
Requires-Dist: tox~=4.11.0; extra == "dev"
Requires-Dist: types-setuptools~=68.1.0.0; extra == "dev"
Requires-Dist: boto3-stubs~=1.34.91; extra == "dev"
Requires-Dist: types-requests~=2.28; extra == "dev"
Dynamic: download-url
Dynamic: license-file
